{
  "appName": "Insurance",
  "navigation": {
    "getQuote": "Get Quote",
    "Help": "Help",
    "Hotline": "Hotline",
    "reportDamage": "Report damage",
    "login": "Login",
    "aboutUs": "About us",
    "languages": "Languages",
    "contact": "Contact us"
  },
  "hero": {
    "payPerKm": "Pay-per-kilemeter",
    "payFullPrice": "Never pay full price again",
    "pointOne": "Insure your car from 1 cent per km",
    "pointTwo": "Save through mileage-based billing",
    "pointThree": "Money back automatically if less driven",
    "getQuote": "Get Quote"
  },
  "services": {
    "parkingDamage": "Parking damage",
    "parkingDamageDescription": "Leverage agile frameworks to provide a robust synopsis for high level overviews.",
    "assistance": "Assistance",
    "assistanceDescription": "Leverage agile frameworks to provide a robust synopsis for high level overviews.",
    "bonusProtection": "Bonus protection",
    "bonusProtectionDescription": "Leverage agile frameworks to provide a robust synopsis for high level overviews.",
    "purchasePriceProtection": "Purchase price protection",
    "purchasePriceProtectionDescription": "Leverage agile frameworks to provide a robust synopsis for high level overviews.",
    "ownDamage": "Own damage",
    "ownDamageDescription": "Leverage agile frameworks to provide a robust synopsis for high level overviews.",
    "innerSpace": "Inner space",
    "innerSpaceDescription": "Leverage agile frameworks to provide a robust synopsis for high level overviews."
  },
  "featured": {
    "trustExperts": "Simply trust experts",
    "pricePerformance": "Insure your car with the price-performance winner",
    "calculateCarInsurance": "Calculate car insurance now"
  },
  "newsletter": {
    "heading": "Wechsel-Alarm: Wir erinnern dich gerne",
    "title": "Du kannst aktuell nicht deine Autoversicherung wechseln? Melde dich gerne für den FRIDAY-Newsletter an und erhalte Informationen zu Produktneuheiten, limitierten Aktionen, persönliche Angebote und nützliche Tipps rund ums Thema Versicherungen.",
    "register": "Anmelden",
    "unsubscribe": "Du kannst dich jederzeit mit dem Abmeldelink in unseren E-Mails oder über unser Kontaktformular abmelden. Weitere Abmeldemöglichkeiten findest Du hier."
  }
}
